[
{
"rating": [
9,
0,
2,
9,
0
],
"permalink": "/r/aww/comments/1twh6je/my_dog_found_the_most_comfy_spot_on_my_wedding_day/",
"url": "https://www.reddit.com/gallery/1twh6je",
"title": "My dog found the most comfy spot on my wedding day",
"selftext": "",
"thumbnail": "https://i.redd.it/w6c6io1t485h1.jpg",
"link_flair_text": "",
"author": "Ok-Conversation7670"
},
{
"rating": [
7,
0,
7,
0,
0
],
"permalink": "/r/meirl/comments/1twgnsp/meirl/",
"url": "https://i.redd.it/cdnrhgqfz75h1.png",
"title": "meirl",
"selftext": "",
"thumbnail": "https://preview.redd.it/cdnrhgqfz75h1.png?width=140&amp;height=140&amp;crop=1:1,smart&amp;auto=webp&amp;s=67dd30f484f02fa79756a8fa88e0a90103d48a19",
"link_flair_text": "",
"author": "Latter-Film-697"
},
{
"rating": [
7,
1,
7,
3,
0
],
"permalink": "/r/funny/comments/1twif77/bear_goes_in_for_another_scratch_but_completely/",
"url": "https://v.redd.it/ifggl51nh85h1",
"title": "Bear goes in for another scratch... but completely misses the tree",
"selftext": "",
"thumbnail": "https://external-preview.redd.it/bTgyOTBwMW5oODVoMT2XEDC7moXQhU5RDsQq_SYmHaeA0mlAq-Je2_fwd3dX.png?format=pjpg&auto=webp&s=63753b7352bd88875604a3d06c3b277421d90293",
"link_flair_text": "",
"author": "Infamous-Window-8337"
},
{
"rating": [
6,
2,
3,
5,
0
],
"permalink": "/r/OldSchoolCool/comments/1twjeik/sabrina_remembered_fondly_by_every_80s_kid/",
"url": "https://v.redd.it/jmkkxro3r85h1",
"title": "Sabrina, remembered fondly by every 80s kid",
"selftext": "",
"thumbnail": "https://external-preview.redd.it/M2VnM2ZmazNyODVoMQPUrD-6-ag4iZ6c073t9Qn43hF0EzxlYzLAvEg6XdHY.png?format=pjpg&auto=webp&s=8f61a2ab07bb109e75847bcdb08219b970d4389c",
"link_flair_text": "flair: 1980s",
"author": "Anuloxisz"
},
{
"rating": [
7,
2,
1,
0,
0
],
"permalink": "/r/AskReddit/comments/1tw2uld/anyone_who_surfed_the_early_web_between_19952010/",
"url": "https://www.reddit.com/r/AskReddit/comments/1tw2uld/anyone_who_surfed_the_early_web_between_19952010/",
"title": "Anyone who surfed the early web between 1995-2010. What\u2019s the one website/app you still think about?",
"selftext": "",
"thumbnail": "self",
"link_flair_text": "",
"author": "Prime_Advocate"
},
{
"rating": [
5,
4,
1,
0,
0
],
"permalink": "/r/mildlyinfuriating/comments/1tvxijv/spam_calls_how_can_i_stop_this_its_a_different/",
"url": "https://i.redd.it/jiap6c2hy35h1.jpeg",
"title": "Spam calls: how can I stop this? It\u2019s a different number all the time. I\u2019ve blocked so many.",
"selftext": "",
"thumbnail": "https://preview.redd.it/jiap6c2hy35h1.jpeg?width=140&amp;height=140&amp;crop=1:1,smart&amp;auto=webp&amp;s=67f92d9723d4b6e5dec9a94bd223e77ec65ce131",
"link_flair_text": "flair: Don't hug me I'm scared",
"author": "EisenFisen"
},
{
"rating": [
6,
2,
1,
0,
0
],
"permalink": "/r/nba/comments/1twbjih/post_game_thread_the_new_york_knicks_10_steal/",
"url": "https://www.reddit.com/r/nba/comments/1twbjih/post_game_thread_the_new_york_knicks_10_steal/",
"title": "[Post Game Thread] The New York Knicks (1-0) steal Game 1 on the road against the San Antonio Spurs (0-1), 105-95, behind Jalen Brunson's 30 point performance",
"selftext": "[ESPN Box Score](https://www.espn.com/nba/boxscore/_/gameId/401859963)\n\n**NBA Finals - Game 1 \u2022 NY leads series 1-0**\n\n|** **|1|2|3|4|T|\n|:-|:-|:-|:-|:-|:-|\n|**NY**|19|29|28|29|105|\n|**SA**|27|28|21|19|95|\n\n|**Team**|FG|FG%|3P|3P%|FT|FT%|REB|AST|STL|BLK|TOV|PF|\n|:-|:-|:-|:-|:-|:-|:-|:-|:-|:-|:-|:-|:-|\n|**NY**|39-94|41%|11-36|31%|16-18|89%|49|20|8|4|9|23|\n|**SA**|32-89|36%|11-43|26%|20-25|80%|54|16|4|4|13|23|\n\n|**New York Knicks**|\u00a0|\u00a0|\u00a0|\u00a0|\u00a0|\u00a0|\u00a0|\u00a0|\u00a0|\u00a0|\u00a0|\u00a0|\u00a0|\u00a0|\n|:-|:-|:-|:-|:-|:-|:-|:-|:-|:-|:-|:-|:-|:-|:-|\n|**Starters**|MIN|PTS|FG|3PT|FT|REB|AST|TO|STL|BLK|OREB|DREB|PF|+/-|\n|**OG Anunoby#8**|31|17|5/12|3/6|4/4|3|0|0|1|1|0|3|0|-6|\n|**Karl-Anthony Towns#32**|34|18|7/15|0-2|4/4|12|4|2|0|1|4|8|4|13|\n|**Josh Hart#3**|27|3|1/5|0-3|1/1|15|6|0|4|1|2|13|4|22|\n|**Mikal Bridges#25**|28|9|3/6|0-0|3/4|3|3|1|2|0|2|1|3|7|\n|**Jalen Brunson#11**|37|30|12/31|2/9|4/4|3|2|4|0|0|1|2|2|6|\n|**Bench**|MIN|PTS|FG|3PT|FT|REB|AST|TO|STL|BLK|OREB|DREB|PF|+/-|\n|**Mitchell Robinson#23**|13|2|1/2|0-0|0-1|6|0|0|0|0|...",
"thumbnail": "self",
"link_flair_text": "flair: Post Game Thread",
"author": "catreyka"
},
{
"rating": [
7,
2,
8,
0,
0
],
"permalink": "/r/pcmasterrace/comments/1twknk2/literally_every_silicon_valley_product_comparison/",
"url": "https://i.redd.it/s5vaj26i295h1.jpeg",
"title": "literally every Silicon Valley product comparison chart:",
"selftext": "",
"thumbnail": "https://preview.redd.it/s5vaj26i295h1.jpeg?width=140&amp;height=96&amp;auto=webp&amp;s=b647441d6e0adc6d6032039896ae406c4115a414",
"link_flair_text": "flair: Meme/Macro",
"author": "ExpensiveCoat8912"
},
{
"rating": [
7,
0,
7,
0,
0
],
"permalink": "/r/GirlDinnerDiaries/comments/1tvzoia/im_on_my_period/",
"url": "https://i.redd.it/7m7vlet9b45h1.jpeg",
"title": "I\u2019m on my period",
"selftext": "Who the fuck is going to stop me\n\nEdit: I knew this was unhinged, but I didn\u2019t think so. Many people would freak out about it.\n\nFor those concerned, I had maybe a tablespoon. So a nice brick of butter, not the entire thing. I am now evening out with an entire tomato. For those suggesting I cover it in sugar, even for me that\u2019s a little bit much\n\nUPDATE: I am still lactose intolerant.\n\n**I AM NOT PREGNANT! I haven\u2019t had sex in THREE YEARS! I\u2019m just fat and hormonal.**",
"thumbnail": "https://preview.redd.it/7m7vlet9b45h1.jpeg?width=140&amp;height=140&amp;crop=1:1,smart&amp;auto=webp&amp;s=881247fbaaf2829f77c96f9a7d35fa6e2125d34c",
"link_flair_text": "flair: Hot Girl Snack \ud83d\udd25 ",
"author": "Bag0Chips"
},
{
"rating": [
2,
0,
1,
0,
0
],
"permalink": "/r/dashcams/comments/1tvveo9/guy_takes_1300_horsepower_car_on_public_streets/",
"url": "https://v.redd.it/igoya8zuk35h1",
"title": "Guy takes 1300 horsepower car on public streets knowing the throttle (gas) sticks, then rides the brakes the entire time to compensate until they fail and he crashes",
"selftext": "",
"thumbnail": "https://external-preview.redd.it/NzF2eHE0MHZrMzVoMeoqHI8C2uAa66rTnqgXsivEMhOW7eAXtYbF8N3dBTTZ.png?format=pjpg&auto=webp&s=f2fad6bdc76d27c7eafe0c3ddb01fd74c5169ae5",
"link_flair_text": "",
"author": "KirkpatrickTemabur"
},
{
"rating": [
7,
1,
7,
2,
0
],
"permalink": "/r/videogames/comments/1twhzbn/girl_is_fighting_for_her_life_in_the_afterlife/",
"url": "https://v.redd.it/9f1s41o1d85h1",
"title": "Girl is fighting for her life in the afterlife \ud83d\ude2d",
"selftext": "",
"thumbnail": "https://external-preview.redd.it/eXl2MHRrcDFkODVoMciMe1n_HviXpCiqlk0nZbx7-V2KhEiJl73rf22N3aPT.png?format=pjpg&auto=webp&s=4837e20439546bc3016401b01756dfd187a8dfc2",
"link_flair_text": "flair: Funny",
"author": "Syarafuddyn"
},
{
"rating": [
2,
1,
0,
0,
8
],
"permalink": "/r/justincaseyoumissedit/comments/1tw3bsu/scenes_from_the_aftermath_of_usisraeli_airstrikes/",
"url": "https://v.redd.it/3g7bc7phy45h1",
"title": "Scenes from the aftermath of U.S.-Israeli airstrikes in Tehran, Iran.",
"selftext": "",
"thumbnail": "https://external-preview.redd.it/a3UweWx2ZWh5NDVoMYBGHtgXZ1skaXKc4O15nsY4Lavy6QIHphbtwcX6kXTJ.png?format=pjpg&auto=webp&s=169618f77cf119262a9b88830cda6cd3f6f47914",
"link_flair_text": "flair: News",
"author": "Outrageous-Spray6160"
},
{
"rating": [
4,
1,
3,
0,
2
],
"permalink": "/r/TikTokCringe/comments/1tw2okf/influencer_upset_when_called_out_for_her/",
"url": "https://v.redd.it/9intdru0u45h1",
"title": "\"Influencer\" upset when called out for her exploitation",
"selftext": "",
"thumbnail": "https://external-preview.redd.it/Y2I2d3BxbDB1NDVoMSiY6ewr6L9oW-94gXTYDHpE5DM9VqcDF4AF22qS23i9.png?format=pjpg&auto=webp&s=253e0c27d23137601abe164f92a41f4b9919fa5a",
"link_flair_text": "flair: Cringe",
"author": "CaptainCorpse666"
},
{
"rating": [
7,
0,
7,
0,
0
],
"permalink": "/r/memes/comments/1twip7o/what_movie_is_this_for_you/",
"url": "https://i.redd.it/99cwc5nek85h1.png",
"title": "What movie is this for you?",
"selftext": "",
"thumbnail": "https://preview.redd.it/99cwc5nek85h1.png?width=140&amp;height=105&amp;auto=webp&amp;s=7eef2d5cdedc5520c59bfa0de2c19df466149cb7",
"link_flair_text": "",
"author": "certainly_imperfect"
},
{
"rating": [
8,
2,
3,
9,
0
],
"permalink": "/r/MadeMeSmile/comments/1twk1oj/tiny_human_tears_dont_stand_a_chance_again_koda/",
"url": "https://v.redd.it/23fx9hg1x85h1",
"title": "Tiny Human Tears don't stand a Chance again Koda and his Fluff.",
"selftext": "",
"thumbnail": "https://external-preview.redd.it/d3J1MzJmYTF4ODVoMWJFHMUr8lG4CE9fPoJ9wMRAhuWCacMx2U-tkHvKo1e4.png?format=pjpg&auto=webp&s=a2fbc6803efca4c0fda82b40e0257ee7e959e12f",
"link_flair_text": "flair: :snoo_hearteyes: Wholesome Moments :snoo_simple_smile:",
"author": "Alternative-Dot-34"
},
{
"rating": [
4,
0,
1,
0,
0
],
"permalink": "/r/NYKnicks/comments/1twbjnw/postgame_thread_new_york_knicks_10_defeat_san/",
"url": "https://www.reddit.com/r/NYKnicks/comments/1twbjnw/postgame_thread_new_york_knicks_10_defeat_san/",
"title": "Post-Game Thread: New York Knicks (1-0) defeat San Antonio Spurs (0-1), 105-95 | NBA Finals | Jun 3, 2026",
"selftext": "This post contains content not supported on old Reddit. [Click here to view the full post](https://sh.reddit.com/r/NYKnicks/comments/1twbjnw)",
"thumbnail": "self",
"link_flair_text": "",
"author": "nba-scores"
},
{
"rating": [
6,
2,
4,
0,
0
],
"permalink": "/r/Damnthatsinteresting/comments/1tvvygv/seattle_light_rail_service_was_suspended_after_a/",
"url": "https://v.redd.it/kheoxhc3p35h1",
"title": "Seattle light rail service was suspended after a driver somehow got their SUV onto the tracks 30 feet above street level",
"selftext": "",
"thumbnail": "https://external-preview.redd.it/M2hmdnNnYjNwMzVoMbXPq9o2eZXi1v3QMzt3naRfJsYZ9V21MIw6wwRyOYIu.png?format=pjpg&auto=webp&s=49bfbdaac218467c9668b252e8c832e586549eaf",
"link_flair_text": "flair: Video",
"author": "Dangerous_Deal_1945"
},
{
"rating": [
3,
1,
4,
0,
0
],
"permalink": "/r/SipsTea/comments/1tvv0jw/robot_kicks_boy_in_stomach_during_performance/",
"url": "https://v.redd.it/928djnhhj35h1",
"title": "Robot kicks boy in stomach during performance",
"selftext": "",
"thumbnail": "https://external-preview.redd.it/Z3czN2xkZmhqMzVoMaTqymYl7PgTolsd7_u7wcT-nM8grcLAA2wfS_BfBpSy.png?format=pjpg&auto=webp&s=63543e93b42dcd04fed60d88da6d81636c5a0001",
"link_flair_text": "flair: Chugging tea :KermitSlowerSip_APNG:",
"author": "Conscious-Weight4569"
},
{
"rating": [
7,
1,
0,
0,
0
],
"permalink": "/r/movies/comments/1tvxb1g/new_poster_for_christopher_nolans_the_odyssey/",
"url": "https://i.redd.it/ugi9wo3bx35h1.jpeg",
"title": "New poster for Christopher Nolan\u2019s \u2018The Odyssey\u2019",
"selftext": "",
"thumbnail": "https://preview.redd.it/ugi9wo3bx35h1.jpeg?width=140&amp;height=140&amp;crop=1:1,smart&amp;auto=webp&amp;s=19c3c2582194a1f2d207e4c8dbffccd178052319",
"link_flair_text": "flair: Poster",
"author": "SpeedForce2022"
},
{
"rating": [
2,
0,
1,
0,
0
],
"permalink": "/r/interestingasfuck/comments/1tvyg6s/robot_goes_rogue_and_kicks_child/",
"url": "https://v.redd.it/nwcwo14l345h1",
"title": "Robot goes rogue and kicks child",
"selftext": "",
"thumbnail": "https://external-preview.redd.it/bTVmcHY3NGwzNDVoMcBgKj4HLHCHMW6U5I-9g3JoLFMAs-isFyhjJQPEUa0h.png?format=pjpg&auto=webp&s=a4bf4c5e3741f026eb641d6acf69d51200d1a4a8",
"link_flair_text": "",
"author": "robbiesloan"
},
{
"rating": [
1,
0,
0,
0,
10
],
"permalink": "/r/politics/comments/1tvro8z/trump_sports_swollen_eye_days_after_surprise/",
"url": "https://newrepublic.com/post/211296/trump-swollen-eye-hand",
"title": "Trump Sports Swollen Eye Days After Surprise Medical Checkup | The president\u2019s eye and hand were visibly swollen as he continues to dodge questions about his health.",
"selftext": "",
"thumbnail": "https://external-preview.redd.it/W459H94Rfxht7sUpu3Z6ycnGYpIvi7-9nD79Pn8jrAk.jpeg?width=140&amp;height=73&amp;auto=webp&amp;s=839f06968520e5ff846ba82453192822ff78561c",
"link_flair_text": "flair: Possible Paywall",
"author": "Aggravating_Money992"
},
{
"rating": [
7,
2,
1,
0,
0
],
"permalink": "/r/mildlyinteresting/comments/1tw1r76/in_5_years_my_clogs_have_worn_off_2cm_of_wood/",
"url": "https://i.redd.it/dirojak9o45h1.png",
"title": "In 5 years my clogs have worn off 2cm of wood",
"selftext": "",
"thumbnail": "https://preview.redd.it/dirojak9o45h1.png?width=140&amp;height=81&amp;auto=webp&amp;s=d8c3acdfe1796fdca781935e69784089dcda8ba4",
"link_flair_text": "",
"author": "01000010-01101001"
},
{
"rating": [
2,
1,
0,
0,
9
],
"permalink": "/r/worldnews/comments/1tvs372/us_officially_announces_reduction_of/",
"url": "https://unn.ua/en/news/the-us-officially-announces-reduction-of-participation-in-nato-forces-suggests-europe-take-on-more-responsibility",
"title": "US officially announces reduction of participation in NATO forces, Europe urged to take on more responsibility",
"selftext": "",
"thumbnail": "https://external-preview.redd.it/lqNoRGIiBvcqS3P8QA-nnR5uy4473bCu_yWlgbTfKHU.jpeg?width=140&amp;height=80&amp;auto=webp&amp;s=8edec878992903bceaa12c96c498d9a4e3bc9c49",
"link_flair_text": "",
"author": "Darshan_brahmbhatt"
},
{
"rating": [
6,
0,
2,
0,
0
],
"permalink": "/r/StarWars/comments/1tw2v2w/which_spaceship_would_you_want_to_fly_the_most/",
"url": "https://www.reddit.com/gallery/1tw2v2w",
"title": "Which spaceship would you want to fly the most?",
"selftext": "**From any of the movies!**",
"thumbnail": "https://i.redd.it/0r22ac6gv45h1.jpg",
"link_flair_text": "flair: General Discussion",
"author": "Thehoobywotzit"
},
{
"rating": [
7,
2,
7,
1,
0
],
"permalink": "/r/comics/comments/1twfnqe/surprise/",
"url": "https://www.reddit.com/gallery/1twfnqe",
"title": "Surprise",
"selftext": "",
"thumbnail": "https://i.redd.it/lsvfm9yap75h1.jpg",
"link_flair_text": "",
"author": "portsherry"
},
{
"rating": [
6,
8,
0,
0,
0
],
"permalink": "/r/news/comments/1twawpa/nearly_60_idahoans_sick_after_drinking_raw_milk/",
"url": "https://idahocapitalsun.com/briefs/nearly-60-idahoans-sick-after-drinking-raw-milk-in-past-two-weeks-officials-say/",
"title": "Nearly 60 Idahoans sick after drinking raw milk in past two weeks, officials say \u2022 Idaho Capital Sun",
"selftext": "",
"thumbnail": "default",
"link_flair_text": "",
"author": "HazyDavey68"
},
{
"rating": [
7,
2,
7,
0,
0
],
"permalink": "/r/ProgrammerHumor/comments/1twif1m/wellwhynot/",
"url": "https://i.redd.it/u7hr9filh85h1.jpeg",
"title": "wellWhyNot",
"selftext": "",
"thumbnail": "https://preview.redd.it/u7hr9filh85h1.jpeg?width=140&amp;height=131&amp;auto=webp&amp;s=4446024169d7c4b73066cc259ae16cda24074811",
"link_flair_text": "flair: Meme",
"author": "soap94"
},
{
"rating": [
4,
3,
0,
0,
1
],
"permalink": "/r/technology/comments/1tvsp3f/spacex_is_worth_less_than_half_of_its_175/",
"url": "https://www.cnbc.com/2026/06/03/morningstar-spacex-ipo-target-price-nasdaq.html",
"title": "SpaceX is worth less than half of its $1.75 trillion IPO target, Morningstar says",
"selftext": "",
"thumbnail": "https://external-preview.redd.it/iVvz67KkkDgWjKsHVjb2CdsYJgTZHGzfYwpFuXODg20.jpeg?width=140&amp;height=78&amp;auto=webp&amp;s=4213f8b0bb0eaed7ebba29252bc6d76004515dcc",
"link_flair_text": "flair: Business",
"author": "idkbruh653"
},
{
"rating": [
7,
0,
7,
0,
0
],
"permalink": "/r/rareinsults/comments/1twg9ad/hes_got_wheelchair_legs/",
"url": "https://i.redd.it/7fg7u9a5v75h1.png",
"title": "He's got wheelchair legs",
"selftext": "",
"thumbnail": "https://preview.redd.it/7fg7u9a5v75h1.png?width=140&amp;height=104&amp;auto=webp&amp;s=39cff6937da0750606baff03ff2f0c094596856a",
"link_flair_text": "",
"author": "Competitive_Owl6466"
},
{
"rating": [
6,
2,
1,
2,
0
],
"permalink": "/r/nba/comments/1twcgfc/highlight_karlanthony_towns_i_just_felt_a_calm/",
"url": "https://streamable.com/9k8ys7",
"title": "[Highlight] Karl-Anthony Towns:\n\n\"I just felt a calm and a peace that had to come from the woman above ... I felt like I was a kid getting ready to go play my Saturday AAU games and Sunday AAU games. In a way, I felt like I was seeing [my mom] in the stands.\"",
"selftext": "",
"thumbnail": "https://external-preview.redd.it/b9-UF0ZqSiJv1bld7Hfyyn5Ac8Td1RTtEw5ChHxBHGQ.jpeg?width=140&amp;height=78&amp;auto=webp&amp;s=a6c8aa5402983a9f97269ca177675345f85a0762",
"link_flair_text": "flair: Highlight",
"author": "BreakfastTop6899"
}
]